gcexplain/__init__.py
gcexplain/functions.py
gcexplain-0.1.2.dist-info/METADATA
gcexplain-0.1.2.dist-info/WHEEL
gcexplain-0.1.2.dist-info/top_level.txt
gcexplain-0.1.2.dist-info/RECORD
