Metadata-Version: 2.1
Name: gcexplain
Version: 0.1.2
Summary: Library for using Granger causality for Feature Importance Estimation
Author: Henrique Peixoto Machado
Requires-Dist: tensorflow ==2.15.0
Requires-Dist: scikit-learn ==1.2.2
Requires-Dist: pandas ==2.0.3
Requires-Dist: numpy ==1.25.2
